poetry_mth/__init__.py
poetry_mth/Address_Book_Handler.py
poetry_mth/addressbook.py
poetry_mth/addressbook_data.py
poetry_mth/AI_helper.py
poetry_mth/GameGooseKiller/font/Candal.ttf
poetry_mth/GameGooseKiller/Game_goose.py
poetry_mth/GameGooseKiller/image/background/1-1.png
poetry_mth/GameGooseKiller/image/background/1-2.png
poetry_mth/GameGooseKiller/image/background/1-3.png
poetry_mth/GameGooseKiller/image/background.png
poetry_mth/GameGooseKiller/image/bonus.png
poetry_mth/GameGooseKiller/image/boom.png
poetry_mth/GameGooseKiller/image/box.png
poetry_mth/GameGooseKiller/image/enemy.png
poetry_mth/GameGooseKiller/image/Farm-Goose.ico
poetry_mth/GameGooseKiller/image/gameover.png
poetry_mth/GameGooseKiller/image/Goose/1-1.png
poetry_mth/GameGooseKiller/image/Goose/1-2.png
poetry_mth/GameGooseKiller/image/Goose/1-3.png
poetry_mth/GameGooseKiller/image/Goose/1-4.png
poetry_mth/GameGooseKiller/image/Goose/1-5.png
poetry_mth/GameGooseKiller/image/heart.svg
poetry_mth/GameGooseKiller/image/lifes/lifes_2.png
poetry_mth/GameGooseKiller/image/lifes/lifes_3.png
poetry_mth/main.py
poetry_mth/Note.py
poetry_mth/Note_Book_Handler.py
poetry_mth/Snake.py
poetry_mth/Sort_Files.py
poetry_mth/Сalculator.py
poetry_mth-0.1.32.dist-info/entry_points.txt
poetry_mth-0.1.32.dist-info/METADATA
poetry_mth-0.1.32.dist-info/WHEEL
poetry_mth-0.1.32.dist-info/RECORD
